{
  // PARAMETER NAME            TYPE               DEFAULT
  
  // diffuse
  "diffuse_color":             {"type": "vec",    "default": [1, 1, 1]   },  // vector3
  "diffuse_map":               {"type": "str",    "default": ""          },  // string
  "use_diffuse_map":           {"type": "bol",    "default": false       },  // boolean
  "diffuse_weight":            {"type": "flt",    "default": 1           },  // float or int
  "diffuse_weight_map":        {"type": "str",    "default": ""          },
  "use_diffuse_weight_map":    {"type": "bol",    "default": false       },
  "diffuse_roughness":         {"type": "flt",    "default": 0           },
  "diffuse_roughness_map":     {"type": "flt",    "default": ""          },
  // ambient
  "ambient_color":             {"type": "vec",    "default": [0, 0, 0]   },
  "ambient_map":               {"type": "str",    "default": ""          },
  "use_ambient_map":           {"type": "bol",    "default": false       },
  "ambient_weight":            {"type": "flt",    "default": 1           },
  "ambient_weight_map":        {"type": "str",    "default": ""          },
  "use_ambient_weight_map":    {"type": "str",    "default": ""          },
  // specular
  "specular_color":		       {"type": "vec",    "default": [0, 0, 0]   },
  "specular_map":		       {"type": "str",    "default": ""          },
  "use_specular_map":	       {"type": "bol",    "default": false       },
  "specular_weight":	       {"type": "flt",    "default": 0.5         },
  "specular_weight_map":       {"type": "str",    "default": ""          },
  "use_specular_weight_map":   {"type": "bol",    "default": false       },
  "specular_roughness":	       {"type": "flt",    "default": 0           },
  "specular_roughness_map":    {"type": "str",    "default": ""          },
  "use_specular_roughness_map":{"type": "bol",    "default": false       },
  "specular_ior":		       {"type": "flt",    "default": 1.5         },
  "specular_anisotropy":       {"type": "flt",    "default": 0           },
  "metallic_weight":	       {"type": "flt",    "default": 0           },
  "metallic_map":		       {"type": "str",    "default": ""          },
  "use_metallic_map":	       {"type": "bol",    "default": false       },
  // refraction
  "refract_color":		       {"type": "vec",    "default": [0, 0, 0]   },
  "refract_weight":		       {"type": "flt",    "default": 0           },
  "refract_roughness":	       {"type": "flt",    "default": 0           },
  "refract_ior":		       {"type": "flt",    "default": 1.5         },
  "refract_dispersion":	       {"type": "flr",    "default": 0           },
  "refract_thin_walled":       {"type": "bol",    "default": false       },
  // opacity
  "opacity_color":             {"type": "vec",    "default": [1, 1, 1]   },
  "opacity_map":               {"type": "str",    "default": ""          },
  "use_opacity_map":           {"type": "bol",    "default": false       },
  "opacity_weight":            {"type": "flt",    "default": 0           },
  "opacity_weight_map":        {"type": "str",    "default": ""          },
  "use_opacity_weight_map":    {"type": "bol",    "default": false       },
  // sss
  "sss_amount":			       {"type": "flt",    "default": 0           },
  "sss_radius":			       {"type": "flt",    "default": 1           },
  "sss_color1":			       {"type": "vec",    "default": [0, 0, 0]   },
  "sss_radius1":		       {"type": "flt",    "default": 0           },
  "sss_weight1":		       {"type": "flt",    "default": 0           },
  "sss_color2":			       {"type": "vec",    "default": [0, 0, 0]   },
  "sss_radius2":	           {"type": "flt",    "default": 0           },
  "sss_weight2":		       {"type": "flt",    "default": 0           },
  "sss_color3":			       {"type": "vec",    "default": [0, 0, 0]   },
  "sss_radius3":		       {"type": "flt",    "default": 0           },
  "sss_weight3":		       {"type": "flt",    "default": 0           },
  // emission
  "emission_color":		       {"type": "vec",    "default": [0, 0, 0]   },
  "emission_map": 		       {"type": "str",    "default": ""          },
  "use_emission_map": 		   {"type": "bol",    "default": false       },
  "emission_weight":	       {"type": "flt",    "default": 0           },
  "emission_weight_map":       {"type": "str",    "default": ""          },
  "use_emission_weight_map":   {"type": "bol",    "default": false       },
  // bump & displace
  "bump_scale":			       {"type": "flt",    "default": 1           },
  "bump_map":			       {"type": "str",    "default": ""          },
  "use_bump_map":              {"type": "bol",    "default": false       },
  "normal_map":             {"type": "str",    "default": ""          },
  "use_normal_map":              {"type": "bol",    "default": false       },
  "displace_height":	       {"type": "flt",    "default": 1           },
  "displace_map":		       {"type": "str",    "default": ""          },
  "use_displace_map":          {"type": "bol",    "default": false       }
  // "some_value"              {"type": "int",    "default": 0           }  int example
}

